AUTHORS
LICENSE
MANIFEST.in
README.md
setup.py
django_yacaptcha.egg-info/PKG-INFO
django_yacaptcha.egg-info/SOURCES.txt
django_yacaptcha.egg-info/dependency_links.txt
django_yacaptcha.egg-info/not-zip-safe
django_yacaptcha.egg-info/requires.txt
django_yacaptcha.egg-info/top_level.txt
yacaptcha/__init__.py
yacaptcha/fields.py
yacaptcha/forms.py
yacaptcha/models.py
yacaptcha/tests.py
yacaptcha/views.py
yacaptcha/widgets.py
yacaptcha/backends/__init__.py
yacaptcha/backends/default/__init__.py
yacaptcha/backends/default/urls.py
yacaptcha/locale/ru/LC_MESSAGES/django.mo
yacaptcha/locale/ru/LC_MESSAGES/django.po
yacaptcha/templates/yacaptcha/widget.html