Metadata-Version: 1.1
Name: django-yacaptcha
Version: 0.0.6
Summary: Simple captcha with Yandex API.
Home-page: http://github.com/Atomic-Creative/django-yacaptcha
Author: avigmati
Author-email: avigmati@gmail.com
License: BSD
Platform: OS Independent
Classifier: Development Status :: 4 - Beta
Classifier: Framework :: Django
Classifier: Intended Audience :: Developers
Classifier: License :: OSI Approved :: BSD License
Classifier: Operating System :: OS Independent
Classifier: Programming Language :: Python
Classifier: Topic :: Internet :: WWW/HTTP
